selenium_tools/__init__.py
selenium_tools-0.0.2.dist-info/LICENSE
selenium_tools-0.0.2.dist-info/METADATA
selenium_tools-0.0.2.dist-info/WHEEL
selenium_tools-0.0.2.dist-info/top_level.txt
selenium_tools-0.0.2.dist-info/RECORD
