Metadata-Version: 2.1
Name: selenium-tools
Version: 0.0.2
Summary: Datetime and range slider tools for python selenium
Home-page: https://dsbowen.github.io/selenium-tools
Author: Dillon Bowen
Author-email: dsbowen@wharton.upenn.edu
License: UNKNOWN
Platform: UNKNOWN
Classifier: Programming Language :: Python :: 3
Classifier: License :: OSI Approved :: MIT License
Classifier: Operating System :: OS Independent
Requires-Python: >=3.6
Requires-Dist: selenium (>=3.141.0)
